{
    "categories": [
        {
            "title": "## 🚀 New Features",
            "labels": ["feat"],
            "pattern": "\\[DS-\\d+\\] - feat"  
        },
        {
            "title": "## 🐛 Fixes",
            "labels": ["fix"],
            "pattern": "\\[DS-\\d+\\] - fix"  
        },
        {
            "title": "## 🔄 Other Updates",
            "labels": ["*"],  
            "pattern": "\\[DS-\\d+\\] - (chore|refactor|docs|test|style|ci)"  
        }
    ],
    "sort": "ASC",
    "template": "${{CHANGELOG}}\n\n<details>\n<summary>Uncategorized</summary>\n\n${{UNCATEGORIZED}}\n</details>",
    "pr_template": "- ${{TITLE}}\n   - PR: #${{NUMBER}}", 
    "empty_template": "- no changes",
    "transformers": [
        {
            "pattern": "\\[DS-\\d+\\] - (feat|fix|chore|refactor|docs|test|style|ci): (.+)",
            "target": "- $2\n   - Type: $1"
        }
    ],
    "max_tags_to_fetch": 200,
    "max_pull_requests": 200,
    "max_back_track_time_days": 90,
    "exclude_merge_branches": [
        "Owner/qa"
    ]
}
